testingmdstuffoksir/__init__.py
testingmdstuffoksir-0.0.5.dist-info/LICENSE
testingmdstuffoksir-0.0.5.dist-info/METADATA
testingmdstuffoksir-0.0.5.dist-info/WHEEL
testingmdstuffoksir-0.0.5.dist-info/top_level.txt
testingmdstuffoksir-0.0.5.dist-info/RECORD
