Metadata-Version: 2.1
Name: testingmdstuffoksir
Version: 0.0.5
Summary: A small example package
Home-page: https://github.com/pypa/sampleproject
Author: EpicCodeWizard2
Author-email: author@example.com
License: UNKNOWN
Platform: UNKNOWN
Classifier: Programming Language :: Python :: 3
Classifier: License :: OSI Approved :: MIT License
Classifier: Operating System :: OS Independent
Requires-Python: >=3.6
